MISA_pySLIME/FILEDOWNLOAD.py
MISA_pySLIME/MISA_pySLIME.py
MISA_pySLIME/__init__.py
MISA_pySLIME/ancillary/processed_ncs/grid_ds_2.0.8.nc
MISA_pySLIME/model/ne_model_2_0_11.npy
MISA_pySLIME/model/ne_model_2_0_5.npy
MISA_pySLIME/model/ne_model_2_0_8.npy
MISA_pySLIME/model/ne_model_2_0_9.npy
MISA_pySLIME/model/ne_model_2_0_9b1.npy
MISA_pySLIME/model/ne_model_2_0_9b2.npy
MISA_pySLIME/model/te_model_2_0_10.npy
MISA_pySLIME/model/te_model_2_0_5.npy
MISA_pySLIME/model/te_model_2_0_8.npy
MISA_pySLIME/model/te_model_2_0_9.npy
MISA_pySLIME/model/te_model_2_0_9b1.npy
MISA_pySLIME/model/te_model_2_0_9b2.npy
MISA_pySLIME/model/ti_model_2_0_10.npy
MISA_pySLIME/model/ti_model_2_0_5.npy
MISA_pySLIME/model/ti_model_2_0_8.npy
MISA_pySLIME/model/ti_model_2_0_9.npy
MISA_pySLIME/model/ti_model_2_0_9b1.npy
MISA_pySLIME/model/ti_model_2_0_9b2.npy
misa_pyslime-2.0.11.3.dist-info/METADATA
misa_pyslime-2.0.11.3.dist-info/WHEEL
misa_pyslime-2.0.11.3.dist-info/top_level.txt
misa_pyslime-2.0.11.3.dist-info/RECORD
