Metadata-Version: 2.4
Name: MISA_pySLIME
Version: 2.0.11.3
Summary: Millstone Hill Incoherent Scatter Radar Spatial-Linear Ionospheric Modeling Engine
Home-page: https://github.com/mcardonaserrano/MISA_pySLIME
Author: Mateo Cardona Serrano (them)
Author-email: mcardonaserrano@berkeley.edu
Classifier: Programming Language :: Python :: 3
Classifier: License :: OSI Approved :: MIT License
Classifier: Operating System :: OS Independent
Requires-Python: >=3.8
Requires-Dist: numpy
Requires-Dist: pandas
Requires-Dist: xarray
Requires-Dist: netCDF4
Requires-Dist: scipy
Requires-Dist: scikit-learn
Requires-Dist: tqdm
Requires-Dist: requests
Dynamic: author
Dynamic: author-email
Dynamic: classifier
Dynamic: description
Dynamic: description-content-type
Dynamic: home-page
Dynamic: requires-dist
Dynamic: requires-python
Dynamic: summary
